graphish/__init__.py
graphish/connector.py
graphish/delete.py
graphish/mailfolder.py
graphish/message.py
graphish/rules.py
graphish/search.py
graphish/users.py
graphish-2.0.0.dist-info/LICENSE
graphish-2.0.0.dist-info/METADATA
graphish-2.0.0.dist-info/WHEEL
graphish-2.0.0.dist-info/top_level.txt
graphish-2.0.0.dist-info/RECORD
