Metadata-Version: 2.1
Name: graphish
Version: 2.0.0
Summary: A Python package to search & delete & move emails using Microsoft Graph API
Home-page: https://github.com/swimlane/graphish
Author: Swimlane
Author-email: info@swimlane.com
License: MIT
Keywords: graph,microsoft,office365,email,ediscovery,phish,phishing,swimlane
Platform: UNKNOWN
Requires-Python: >=3.6, <4
License-File: LICENSE
Requires-Dist: requests
Requires-Dist: oauthlib
Requires-Dist: pendulum
Requires-Dist: requests-oauthlib
